README.md
inst341data.py
setup.py
inst341data.egg-info/PKG-INFO
inst341data.egg-info/SOURCES.txt
inst341data.egg-info/dependency_links.txt
inst341data.egg-info/top_level.txt