Metadata-Version: 1.0
Name: inst341data
Version: 0.0.7
Summary: install data in jupyter notebook
Home-page: https://github.com/edsu/inst341data
Author: Ed Summers
Author-email: ehs@pobox.com
License: UNKNOWN
Platform: UNKNOWN
